pydeck_randyiscoding/__about__.py
pydeck_randyiscoding/__init__.py
pydeck_randyiscoding/card.py
pydeck_randyiscoding/deck_of_cards.py
pydeck_randyiscoding/properties.py
pydeck_randyiscoding-0.0.1.dist-info/METADATA
pydeck_randyiscoding-0.0.1.dist-info/WHEEL
pydeck_randyiscoding-0.0.1.dist-info/licenses/LICENSE
pydeck_randyiscoding-0.0.1.dist-info/RECORD
