Metadata-Version: 2.4
Name: pydeck_randyiscoding
Version: 0.0.1
Summary: Creates a 52 Card Deck (No Jokers or other extra cards)
Project-URL: Homepage, https://github.com/randyiscoding/pydeck
Project-URL: Issues, https://github.com/randyiscoding/pydeck/issues
Author-email: Randy Easton <reaston@my365.bellevue.edu>
License-Expression: MIT
License-File: LICENSE
Classifier: Operating System :: OS Independent
Classifier: Programming Language :: Python :: 3
Requires-Python: >=3.9
